pyjxl/__init__.py
pyjxl-0.1.0.dist-info/WHEEL
pyjxl-0.1.0.dist-info/METADATA
pyjxl-0.1.0.dist-info/RECORD
