Metadata-Version: 2.1
Name: pyjxl
Version: 0.1.0
Summary: 
Author: Aravind Reddy Voggu
Author-email: aravind.reddy@iiitb.org
Requires-Python: >=3.10,<4.0
Classifier: Programming Language :: Python :: 3
Classifier: Programming Language :: Python :: 3.10
Classifier: Programming Language :: Python :: 3.11
